pack2/Bullsncows.py
pack2/RocknPapernScissors.py
pack2/__init__.py
pack2/guessNumber.py
games_hitesh14-1.0.0.dist-info/METADATA
games_hitesh14-1.0.0.dist-info/WHEEL
games_hitesh14-1.0.0.dist-info/top_level.txt
games_hitesh14-1.0.0.dist-info/RECORD
