Metadata-Version: 2.4
Name: games-hitesh14
Version: 1.0.0
Summary: A collection of fun games: Bulls and Cows, Guess the Number, Rock Paper Scissors.
Home-page: https://github.com/hitesh14/games
Author: Hitesh
Keywords: games,fun,bulls and cows,guess the number,rock paper scissors
Classifier: Programming Language :: Python :: 3
Classifier: License :: OSI Approved :: MIT License
Classifier: Operating System :: OS Independent
Classifier: Topic :: Games/Entertainment
Classifier: Intended Audience :: End Users/Desktop
Requires-Python: >=3.6
Dynamic: author
Dynamic: classifier
Dynamic: description
Dynamic: description-content-type
Dynamic: home-page
Dynamic: keywords
Dynamic: requires-python
Dynamic: summary
